dbff.py
setup.py
dbff.egg-info/PKG-INFO
dbff.egg-info/SOURCES.txt
dbff.egg-info/dependency_links.txt
dbff.egg-info/requires.txt
dbff.egg-info/top_level.txt