Metadata-Version: 1.0
Name: dbff
Version: 1.4.4
Summary: Compare tables and rows between MySQL databases.
Home-page: https://github.com/yosg/dbff
Author: Xiayi Li
Author-email: hi@xiayi.li
License: MIT License
Platform: UNKNOWN
